sbx2hf.py
sbx2hf-0.1.1.dist-info/METADATA
sbx2hf-0.1.1.dist-info/WHEEL
sbx2hf-0.1.1.dist-info/licenses/LICENSE
sbx2hf-0.1.1.dist-info/RECORD
