Metadata-Version: 2.4
Name: sbx2hf
Version: 0.1.1
Summary: A tool to automatically upload a Språkbanken resource to the Hugging Face Hub.
Author-email: Felix Morger <felix.morger@gu.se>
License: The GNU General Public License v3.0
License-File: LICENSE
Requires-Python: >=3.11
Requires-Dist: huggingface-hub~=0.26.2
Requires-Dist: jinja2~=3.1.4
Requires-Dist: pandas~=2.2.3
Requires-Dist: requests~=2.31.0
